LICENSE
README.md
setup.cfg
setup.py
pyLiang/__init__.py
pyLiang/liang.py
pyLiang.egg-info/PKG-INFO
pyLiang.egg-info/SOURCES.txt
pyLiang.egg-info/dependency_links.txt
pyLiang.egg-info/requires.txt
pyLiang.egg-info/top_level.txt